pysevdesk/__init__.py
pysevdesk/api_client.py
pysevdesk/api_response.py
pysevdesk/configuration.py
pysevdesk/exceptions.py
pysevdesk/py.typed
pysevdesk/rest.py
pysevdesk/api/__init__.py
pysevdesk/api/accounting_contact_api.py
pysevdesk/api/basics_api.py
pysevdesk/api/check_account_api.py
pysevdesk/api/check_account_transaction_api.py
pysevdesk/api/communication_way_api.py
pysevdesk/api/contact_address_api.py
pysevdesk/api/contact_api.py
pysevdesk/api/contact_field_api.py
pysevdesk/api/credit_note_api.py
pysevdesk/api/credit_note_pos_api.py
pysevdesk/api/export_api.py
pysevdesk/api/invoice_api.py
pysevdesk/api/invoice_pos_api.py
pysevdesk/api/layout_api.py
pysevdesk/api/order_api.py
pysevdesk/api/order_pos_api.py
pysevdesk/api/part_api.py
pysevdesk/api/report_api.py
pysevdesk/api/tag_api.py
pysevdesk/api/voucher_api.py
pysevdesk/api/voucher_pos_api.py
pysevdesk/models/__init__.py
pysevdesk/models/book_credit_note200_response.py
pysevdesk/models/book_credit_note200_response_credit_note.py
pysevdesk/models/book_credit_note200_response_sev_client.py
pysevdesk/models/book_credit_note_request.py
pysevdesk/models/book_credit_note_request_check_account.py
pysevdesk/models/book_credit_note_request_check_account_transaction.py
pysevdesk/models/book_invoice200_response.py
pysevdesk/models/book_invoice200_response_credit_note.py
pysevdesk/models/book_invoice200_response_sev_client.py
pysevdesk/models/book_invoice_request.py
pysevdesk/models/book_invoice_request_check_account_transaction.py
pysevdesk/models/book_voucher200_response.py
pysevdesk/models/book_voucher200_response_credit_note.py
pysevdesk/models/book_voucher_request.py
pysevdesk/models/book_voucher_request_check_account_transaction.py
pysevdesk/models/bookkeeping_system_version200_response.py
pysevdesk/models/bookkeeping_system_version200_response_objects.py
pysevdesk/models/check_account_transaction_enshrine200_response.py
pysevdesk/models/contact_customer_number_availability_check200_response.py
pysevdesk-0.1.0.dist-info/METADATA
pysevdesk-0.1.0.dist-info/WHEEL
pysevdesk-0.1.0.dist-info/top_level.txt
pysevdesk-0.1.0.dist-info/RECORD
